krons/__init__.py
krons/errors.py
krons/protocols.py
krons/py.typed
krons/core/__init__.py
krons/core/broadcaster.py
krons/core/element.py
krons/core/event.py
krons/core/eventbus.py
krons/core/flow.py
krons/core/graph.py
krons/core/node.py
krons/core/pile.py
krons/core/processor.py
krons/core/progression.py
krons/enforcement/__init__.py
krons/enforcement/context.py
krons/enforcement/policy.py
krons/enforcement/registry.py
krons/enforcement/rule.py
krons/enforcement/service.py
krons/enforcement/validator.py
krons/enforcement/common/__init__.py
krons/enforcement/common/boolean.py
krons/enforcement/common/choice.py
krons/enforcement/common/mapping.py
krons/enforcement/common/model.py
krons/enforcement/common/number.py
krons/enforcement/common/string.py
krons/operations/__init__.py
krons/operations/builder.py
krons/operations/flow.py
krons/operations/node.py
krons/operations/registry.py
krons/services/__init__.py
krons/services/backend.py
krons/services/endpoint.py
krons/services/hook.py
krons/services/imodel.py
krons/services/registry.py
krons/services/utilities/__init__.py
krons/services/utilities/header_factory.py
krons/services/utilities/rate_limited_executor.py
krons/services/utilities/rate_limiter.py
krons/services/utilities/resilience.py
krons/session/__init__.py
krons/session/exchange.py
krons/session/message.py
krons/session/session.py
krons/specs/__init__.py
krons/specs/factory.py
krons/specs/operable.py
krons/specs/phrase.py
krons/specs/protocol.py
krons/specs/spec.py
krons/specs/adapters/__init__.py
krons/specs/adapters/_utils.py
krons/specs/adapters/dataclass_field.py
krons/specs/adapters/factory.py
krons/specs/adapters/pydantic_adapter.py
krons/specs/adapters/sql_ddl.py
krons/specs/catalog/__init__.py
krons/specs/catalog/_audit.py
krons/specs/catalog/_common.py
krons/specs/catalog/_content.py
krons/specs/catalog/_enforcement.py
krons/types/__init__.py
krons/types/_sentinel.py
krons/types/base.py
krons/types/db_types.py
krons/types/identity.py
krons-0.1.1.dist-info/METADATA
krons-0.1.1.dist-info/WHEEL
krons-0.1.1.dist-info/licenses/LICENSE
krons-0.1.1.dist-info/RECORD
