Metadata-Version: 2.4
Name: krons
Version: 0.1.1
Summary: Spec-based composable framework for building type-safe systems
Project-URL: Homepage, https://github.com/khive-ai/krons
Project-URL: Repository, https://github.com/khive-ai/krons
Project-URL: Issues, https://github.com/khive-ai/krons/issues
Author-email: HaiyangLi <quantocean.li@gmail.com>
License-Expression: Apache-2.0
License-File: LICENSE
Keywords: composable,framework,pydantic,spec,type-safe,validation
Classifier: Development Status :: 4 - Beta
Classifier: Intended Audience :: Developers
Classifier: License :: OSI Approved :: Apache Software License
Classifier: Programming Language :: Python :: 3
Classifier: Programming Language :: Python :: 3.11
Classifier: Programming Language :: Python :: 3.12
Classifier: Topic :: Software Development :: Libraries :: Python Modules
Classifier: Typing :: Typed
Requires-Python: >=3.11
Requires-Dist: anyio>=4.10.0
Requires-Dist: httpx>=0.26.0
Requires-Dist: orjson>=3.10.0
Requires-Dist: pydantic>=2.10.0
Requires-Dist: rapidfuzz>=3.10.0
